README.md
__init__.py
exceptions.py
security_group_auditor.py
setup.py
test.py
security_group_auditor.egg-info/PKG-INFO
security_group_auditor.egg-info/SOURCES.txt
security_group_auditor.egg-info/dependency_links.txt
security_group_auditor.egg-info/requires.txt
security_group_auditor.egg-info/top_level.txt